<hp:p xmlns:hp="http://www.hancom.co.kr/hwpml/2011/paragraph" id="0" paraPrIDRef="31" styleIDRef="0" pageBreak="0" columnBreak="0" merged="0"><hp:run charPrIDRef="0"><hp:ctrl><hp:pageHiding hideHeader="1" hideFooter="0" hideMasterPage="0" hideBorder="0" hideFill="0" hidePageNum="1" /></hp:ctrl><hp:tbl id="1532694252" zOrder="6" numberingType="TABLE" textWrap="TOP_AND_BOTTOM" textFlow="BOTH_SIDES" lock="0" dropcapstyle="None" pageBreak="NONE" repeatHeader="1" rowCnt="3" colCnt="3" cellSpacing="0" borderFillIDRef="4" noAdjust="1"><hp:sz width="48180" widthRelTo="ABSOLUTE" height="12690" heightRelTo="ABSOLUTE" protect="0" /><hp:pos treatAsChar="1" affectLSpacing="0" flowWithText="0" allowOverlap="0" holdAnchorAndSO="1" vertRelTo="PARA" horzRelTo="PARA" vertAlign="TOP" horzAlign="LEFT" vertOffset="0" horzOffset="0" /><hp:outMargin left="0" right="0" top="0" bottom="0" /><hp:inMargin left="0" right="0" top="0" bottom="0" /><hp:tr><hp:tc name="" header="0" hasMargin="0" protect="0" editable="0" dirty="0" borderFillIDRef="7"><hp:subList id="" textDirection="HORIZONTAL" lineWrap="BREAK" vertAlign="CENTER" linkListIDRef="0" linkListNextIDRef="0" textWidth="0" textHeight="0" hasTextRef="0" hasNumRef="0"><hp:p id="2147483648" paraPrIDRef="26" styleIDRef="0" pageBreak="0" columnBreak="0" merged="0"><hp:run charPrIDRef="16" /><hp:linesegarray><hp:lineseg textpos="0" vertpos="0" vertsize="600" textheight="600" baseline="510" spacing="-176" horzpos="0" horzsize="38216" flags="393216" /></hp:linesegarray></hp:p></hp:subList><hp:cellAddr colAddr="0" rowAddr="0" /><hp:cellSpan colSpan="2" rowSpan="1" /><hp:cellSz width="38219" height="818" /><hp:cellMargin left="0" right="0" top="0" bottom="0" /></hp:tc><hp:tc name="" header="0" hasMargin="0" protect="0" editable="0" dirty="0" borderFillIDRef="8"><hp:subList id="" textDirection="HORIZONTAL" lineWrap="BREAK" vertAlign="CENTER" linkListIDRef="0" linkListNextIDRef="0" textWidth="0" textHeight="0" hasTextRef="0" hasNumRef="0"><hp:p id="2147483648" paraPrIDRef="27" styleIDRef="0" pageBreak="0" columnBreak="0" merged="0"><hp:run charPrIDRef="16" /><hp:linesegarray><hp:lineseg textpos="0" vertpos="0" vertsize="600" textheight="600" baseline="510" spacing="-32" horzpos="0" horzsize="9960" flags="393216" /></hp:linesegarray></hp:p></hp:subList><hp:cellAddr colAddr="2" rowAddr="0" /><hp:cellSpan colSpan="1" rowSpan="1" /><hp:cellSz width="9961" height="818" /><hp:cellMargin left="0" right="0" top="0" bottom="0" /></hp:tc></hp:tr><hp:tr><hp:tc name="" header="0" hasMargin="0" protect="0" editable="0" dirty="0" borderFillIDRef="4"><hp:subList id="" textDirection="HORIZONTAL" lineWrap="BREAK" vertAlign="CENTER" linkListIDRef="0" linkListNextIDRef="0" textWidth="0" textHeight="0" hasTextRef="0" hasNumRef="0"><hp:p id="2147483648" paraPrIDRef="23" styleIDRef="0" pageBreak="0" columnBreak="0" merged="0"><hp:run charPrIDRef="22"><hp:t>기본 보고서 양식</hp:t></hp:run><hp:linesegarray><hp:lineseg textpos="0" vertpos="0" vertsize="3000" textheight="3000" baseline="2550" spacing="900" horzpos="0" horzsize="48180" flags="393216" /></hp:linesegarray></hp:p></hp:subList><hp:cellAddr colAddr="0" rowAddr="1" /><hp:cellSpan colSpan="3" rowSpan="1" /><hp:cellSz width="48180" height="11060" /><hp:cellMargin left="0" right="0" top="0" bottom="0" /></hp:tc></hp:tr><hp:tr><hp:tc name="" header="0" hasMargin="0" protect="0" editable="0" dirty="0" borderFillIDRef="7"><hp:subList id="" textDirection="HORIZONTAL" lineWrap="BREAK" vertAlign="CENTER" linkListIDRef="0" linkListNextIDRef="0" textWidth="0" textHeight="0" hasTextRef="0" hasNumRef="0"><hp:p id="2147483648" paraPrIDRef="27" styleIDRef="0" pageBreak="0" columnBreak="0" merged="0"><hp:run charPrIDRef="17" /><hp:linesegarray><hp:lineseg textpos="0" vertpos="0" vertsize="600" textheight="600" baseline="510" spacing="-32" horzpos="0" horzsize="10464" flags="393216" /></hp:linesegarray></hp:p></hp:subList><hp:cellAddr colAddr="0" rowAddr="2" /><hp:cellSpan colSpan="1" rowSpan="1" /><hp:cellSz width="10466" height="812" /><hp:cellMargin left="0" right="0" top="0" bottom="0" /></hp:tc><hp:tc name="" header="0" hasMargin="0" protect="0" editable="0" dirty="0" borderFillIDRef="8"><hp:subList id="" textDirection="HORIZONTAL" lineWrap="BREAK" vertAlign="CENTER" linkListIDRef="0" linkListNextIDRef="0" textWidth="0" textHeight="0" hasTextRef="0" hasNumRef="0"><hp:p id="2147483648" paraPrIDRef="27" styleIDRef="0" pageBreak="0" columnBreak="0" merged="0"><hp:run charPrIDRef="17" /><hp:linesegarray><hp:lineseg textpos="0" vertpos="0" vertsize="600" textheight="600" baseline="510" spacing="-32" horzpos="0" horzsize="37712" flags="393216" /></hp:linesegarray></hp:p></hp:subList><hp:cellAddr colAddr="1" rowAddr="2" /><hp:cellSpan colSpan="2" rowSpan="1" /><hp:cellSz width="37714" height="812" /><hp:cellMargin left="0" right="0" top="0" bottom="0" /></hp:tc></hp:tr></hp:tbl><hp:t /></hp:run></hp:p>